mu_pipelines_secrets/__init__.py
mu_pipelines_secrets/env_secrets/__init__.py
mu_pipelines_secrets/env_secrets/env_secrets.py
mu_pipelines_secrets-0.1.0a0.dist-info/entry_points.txt
mu_pipelines_secrets-0.1.0a0.dist-info/licenses/LICENSE
mu_pipelines_secrets-0.1.0a0.dist-info/WHEEL
mu_pipelines_secrets-0.1.0a0.dist-info/METADATA
mu_pipelines_secrets-0.1.0a0.dist-info/RECORD
