Metadata-Version: 2.4
Name: mu_pipelines_secrets
Version: 0.1.0a0
Summary: mu_pipelines_secrets
Keywords: data movement,spark,etl
Author-email: MosaicSoft <mupipelines@gmail.com>
Requires-Python: >=3.12
Classifier: Programming Language :: Python :: 3
License-File: LICENSE
Requires-Dist: mu-pipelines-interfaces >=0.2.0a0
